pyraisdk/__init__.py
pyraisdk/dynbatch/__init__.py
pyraisdk/dynbatch/base.py
pyraisdk/dynbatch/batch.py
pyraisdk/dynbatch/config.py
pyraisdk/dynconfig/__init__.py
pyraisdk/dynconfig/common.py
pyraisdk/dynconfig/core.py
pyraisdk/dynconfig/monitor.py
pyraisdk/dynconfig/proxy.py
pyraisdk/dynconfig/shim.py
pyraisdk/dynconfig/utils.py
pyraisdk/rlog/__init__.py
pyraisdk/rlog/eventhub.py
pyraisdk/rlog/gputil.py
pyraisdk/rlog/log.py
pyraisdk/rlog/logimp.py
pyraisdk/rlog/reporter.py
pyraisdk_test-0.3.13.dist-info/METADATA
pyraisdk_test-0.3.13.dist-info/WHEEL
pyraisdk_test-0.3.13.dist-info/entry_points.txt
pyraisdk_test-0.3.13.dist-info/RECORD
