Metadata-Version: 2.1
Name: pyraisdk-test
Version: 0.3.13
Summary: 
Author: Xiaodong Yang
Author-email: xiaoyan@microsoft.com
Requires-Python: >=3.8,<4.0
Classifier: Programming Language :: Python :: 3
Classifier: Programming Language :: Python :: 3.8
Classifier: Programming Language :: Python :: 3.9
Classifier: Programming Language :: Python :: 3.10
Classifier: Programming Language :: Python :: 3.11
Classifier: Programming Language :: Python :: 3.12
Requires-Dist: aiohttp (>=3.8.5,<4.0.0)
Requires-Dist: azure-cosmos (>=4.5.0,<5.0.0)
Requires-Dist: azure-eventhub (>=5.10.1,<6.0.0)
Requires-Dist: azure-identity (>=1.7.0,<2.0.0)
Requires-Dist: dataclasses-json (>=0.5.7,<0.6.0)
Requires-Dist: flask
Requires-Dist: psutil (>=5.6.3,<6.0.0)
Requires-Dist: pydantic (>=1.10.9,<3.0.0)
